watchdoc/__init__.py
watchdoc/docx_manager.py
watchdoc/folder_manager.py
watchdoc/image_manager.py
watchdoc/markdown_manager.py
watchdoc/odt_manager.py
watchdoc/pptx_manager.py
watchdoc/table_of_contents.py
watchdoc/update_docs.py
watchdoc/watch_docs.py
watchdoc-0.0.1.dist-info/LICENCE
watchdoc-0.0.1.dist-info/METADATA
watchdoc-0.0.1.dist-info/WHEEL
watchdoc-0.0.1.dist-info/top_level.txt
watchdoc-0.0.1.dist-info/RECORD
