Metadata-Version: 2.1
Name: watchdoc
Version: 0.0.1
Summary: Markdown and Jupyter Notebook file watcher. It generates automatically a docx, a pptx, and a pdf for each md or ipynb file.
Home-page: https://github.com/yilmazchef/pip-notebooks/
Author: Yilmaz Mustafa
Author-email: chef@mail.be
License: UNKNOWN
Project-URL: Bug Tracker, https://github.com/yilmazchef/pip-notebooks/issues
Platform: UNKNOWN
Classifier: Programming Language :: Python :: 3
Classifier: License :: OSI Approved :: MIT License
Classifier: Operating System :: OS Independent
Requires-Python: >=3.7
License-File: LICENCE
